{
  "data": [
    {
      "id_photo": 456239174,
      "url_small": "https://picsum.photos/id/1053/600",
      "url_big": "https://picsum.photos/id/1053/900",
      "name": "",
      "description": ""
    },
    {
      "id_photo": 456239145,
      "url_small": "https://source.unsplash.com/L1y9f5O8wiA/600",
      "url_big": "https://source.unsplash.com/L1y9f5O8wiA/960",
      "name": "Unsplash",
      "description": ""
    },
    {
      "id_photo": 456239152,
      "url_small": "https://source.unsplash.com/t2Sai-AqIpI/w=600",
      "url_big": "https://source.unsplash.com/t2Sai-AqIpI/w=960",
      "name": "Painting",
      "description": ""
    },
    {
      "id_photo": 456239107,
      "url_small": "https://source.unsplash.com/eAwzwVZNlw8/w=600",
      "url_big": "https://source.unsplash.com/t2Sai-AqIpI/w=960",
      "name": "",
      "description": "Some description"
    }
  ]
}
